[
  {
    "Id": "68357bed6d966c2c14858d05",
    "Name": "Kiknik Toofsnatcha",
    "Type": "Profile",
    "BaseId": "7",
    "Children": [
      {
        "Id": "statline_511"
      },
      {
        "Id": "statline_512"
      },
      {
        "Id": "rule_455"
      },
      {
        "Id": "rule_166"
      },
      {
        "Id": "rule_30",
        "Info": "(1, Chompa only)"
      },
      {
        "Id": "rule_62",
        "Info": "(1)"
      },
      {
        "Id": "rule_48"
      },
      {
        "Id": "rule_456"
      },
      {
        "Id": "rule_33"
      },
      {
        "Id": "rule_457"
      },
      {
        "Id": "rule_117"
      },
      {
        "Id": "rule_127"
      },
      {
        "Id": "rule_8"
      },
      {
        "Id": "rule_11"
      },
      {
        "Id": "rule_458"
      },
      {
        "Id": "rule_29"
      },
      {
        "Id": "rule_459",
        "Info": "(Hammer)"
      },
      {
        "Id": "rule_460",
        "Info": "(Pick)"
      },
      {
        "Id": "rule_47"
      },
      {
        "Id": "rule_49"
      },
      {
        "Id": "rule_12"
      }
    ]
  },
  {
    "Id": "68357bed6d966c2c14858f83",
    "Name": "Ogdruz Swampdigga",
    "Type": "Profile",
    "BaseId": "2",
    "Children": [
      {
        "Id": "statline_513"
      },
      {
        "Id": "rule_121"
      },
      {
        "Id": "rule_461"
      },
      {
        "Id": "rule_130"
      },
      {
        "Id": "rule_462"
      },
      {
        "Id": "rule_463"
      },
      {
        "Id": "rule_11"
      },
      {
        "Id": "rule_464"
      },
      {
        "Id": "rule_365"
      },
      {
        "Id": "rule_465"
      },
      {
        "Id": "rule_466"
      }
    ]
  },
  {
    "Id": "68357bed6d966c2c148591ec",
    "Name": "Goblin Bigboss",
    "Type": "Profile",
    "BaseId": "4",
    "Children": [
      {
        "Id": "statline_514"
      },
      {
        "Id": "rule_457"
      },
      {
        "Id": "rule_117"
      },
      {
        "Id": "rule_127"
      },
      {
        "Id": "rule_11"
      },
      {
        "Id": "rule_12"
      }
    ]
  },
  {
    "Id": "eab1595c-cb8d-4bbc-96cd-c19d3ff7d2bf",
    "Name": "Goblin Bigboss on Goblin Wolf Chariot",
    "Type": "Profile",
    "BaseId": "5",
    "Children": [
      {
        "Id": "statline_514"
      },
      {
        "Id": "statline_515"
      },
      {
        "Id": "statline_516"
      },
      {
        "Id": "statline_517"
      },
      {
        "Id": "rule_457"
      },
      {
        "Id": "rule_25",
        "Info": "(D3+1)"
      },
      {
        "Id": "rule_117"
      },
      {
        "Id": "rule_40"
      },
      {
        "Id": "rule_127"
      },
      {
        "Id": "rule_8"
      },
      {
        "Id": "rule_11"
      },
      {
        "Id": "rule_27"
      },
      {
        "Id": "rule_12"
      },
      {
        "Id": "rule_29"
      },
      {
        "Id": "rule_320"
      }
    ]
  },
  {
    "Id": "8f6808bd-4d94-4f15-91db-84750dad90fc",
    "Name": "Goblin Bigboss on Gigantic Spider",
    "Type": "Profile",
    "BaseId": "6",
    "Children": [
      {
        "Id": "statline_514"
      },
      {
        "Id": "statline_518"
      },
      {
        "Id": "rule_62",
        "Info": "(1)"
      },
      {
        "Id": "rule_33"
      },
      {
        "Id": "rule_457"
      },
      {
        "Id": "rule_117"
      },
      {
        "Id": "rule_5"
      },
      {
        "Id": "rule_78"
      },
      {
        "Id": "rule_127"
      },
      {
        "Id": "rule_8"
      },
      {
        "Id": "rule_11"
      },
      {
        "Id": "rule_12"
      }
    ]
  },
  {
    "Id": "6a945ee3-89b1-41f1-975c-18c3eb4093d7",
    "Name": "Goblin Bigboss on Giant Wolf",
    "Type": "Profile",
    "BaseId": "7",
    "Children": [
      {
        "Id": "statline_514"
      },
      {
        "Id": "statline_69"
      },
      {
        "Id": "rule_457"
      },
      {
        "Id": "rule_117"
      },
      {
        "Id": "rule_127"
      },
      {
        "Id": "rule_11"
      },
      {
        "Id": "rule_12"
      }
    ]
  },
  {
    "Id": "68357bee6d966c2c1485bc26",
    "Name": "Goblin Oddgit",
    "Type": "Profile",
    "BaseId": "4",
    "Children": [
      {
        "Id": "statline_519"
      },
      {
        "Id": "rule_457"
      },
      {
        "Id": "rule_467"
      },
      {
        "Id": "rule_11"
      },
      {
        "Id": "rule_12"
      },
      {
        "Id": "rule_468"
      },
      {
        "Id": "rule_469"
      }
    ]
  },
  {
    "Id": "17aa1fbb-2210-4757-8837-55648b71cbb9",
    "Name": "Goblin Oddgit on Goblin Wolf Chariot",
    "Type": "Profile",
    "BaseId": "5",
    "Children": [
      {
        "Id": "statline_519"
      },
      {
        "Id": "statline_515"
      },
      {
        "Id": "statline_516"
      },
      {
        "Id": "statline_517"
      },
      {
        "Id": "rule_457"
      },
      {
        "Id": "rule_25",
        "Info": "(D3+1)"
      },
      {
        "Id": "rule_117"
      },
      {
        "Id": "rule_467"
      },
      {
        "Id": "rule_40"
      },
      {
        "Id": "rule_8"
      },
      {
        "Id": "rule_11"
      },
      {
        "Id": "rule_27"
      },
      {
        "Id": "rule_12"
      },
      {
        "Id": "rule_29"
      },
      {
        "Id": "rule_320"
      }
    ]
  },
  {
    "Id": "fd2a4f83-ea29-4ff5-9ecb-2a414f6150d4",
    "Name": "Goblin Oddgit on Giant Wolf",
    "Type": "Profile",
    "BaseId": "7",
    "Children": [
      {
        "Id": "statline_519"
      },
      {
        "Id": "statline_69"
      },
      {
        "Id": "rule_457"
      },
      {
        "Id": "rule_467"
      },
      {
        "Id": "rule_11"
      },
      {
        "Id": "rule_12"
      }
    ]
  },
  {
    "Id": "68357bef6d966c2c1485da72",
    "Name": "Goblin Oddnob",
    "Type": "Profile",
    "BaseId": "4",
    "Children": [
      {
        "Id": "statline_520"
      },
      {
        "Id": "rule_457"
      },
      {
        "Id": "rule_467"
      },
      {
        "Id": "rule_11"
      },
      {
        "Id": "rule_12"
      },
      {
        "Id": "rule_468"
      },
      {
        "Id": "rule_469"
      }
    ]
  },
  {
    "Id": "c0410904-f12c-4e0f-baa8-9b1b0f7df172",
    "Name": "Goblin Oddnob on Goblin Wolf Chariot",
    "Type": "Profile",
    "BaseId": "5",
    "Children": [
      {
        "Id": "statline_520"
      },
      {
        "Id": "statline_515"
      },
      {
        "Id": "statline_516"
      },
      {
        "Id": "statline_517"
      },
      {
        "Id": "rule_457"
      },
      {
        "Id": "rule_25",
        "Info": "(D3+1)"
      },
      {
        "Id": "rule_117"
      },
      {
        "Id": "rule_467"
      },
      {
        "Id": "rule_40"
      },
      {
        "Id": "rule_8"
      },
      {
        "Id": "rule_11"
      },
      {
        "Id": "rule_27"
      },
      {
        "Id": "rule_12"
      },
      {
        "Id": "rule_29"
      },
      {
        "Id": "rule_320"
      }
    ]
  },
  {
    "Id": "91dd2fed-829e-4142-9946-182d6a7022d7",
    "Name": "Goblin Oddnob on Arachnarok Spider",
    "Type": "Profile",
    "BaseId": "12",
    "Children": [
      {
        "Id": "statline_520"
      },
      {
        "Id": "statline_521"
      },
      {
        "Id": "statline_522"
      },
      {
        "Id": "rule_22"
      },
      {
        "Id": "rule_457"
      },
      {
        "Id": "rule_452"
      },
      {
        "Id": "rule_57"
      },
      {
        "Id": "rule_52"
      },
      {
        "Id": "rule_467"
      },
      {
        "Id": "rule_5"
      },
      {
        "Id": "rule_78"
      },
      {
        "Id": "rule_7",
        "Info": "(D6)"
      },
      {
        "Id": "rule_59"
      },
      {
        "Id": "rule_8"
      },
      {
        "Id": "rule_54"
      },
      {
        "Id": "rule_11"
      },
      {
        "Id": "rule_27"
      },
      {
        "Id": "rule_12"
      },
      {
        "Id": "rule_470"
      },
      {
        "Id": "rule_29"
      },
      {
        "Id": "rule_320"
      }
    ]
  },
  {
    "Id": "e7e38f45-0af6-4b60-b873-a7587db17fe0",
    "Name": "Goblin Oddnob on Giant Wolf",
    "Type": "Profile",
    "BaseId": "7",
    "Children": [
      {
        "Id": "statline_520"
      },
      {
        "Id": "statline_69"
      },
      {
        "Id": "rule_457"
      },
      {
        "Id": "rule_467"
      },
      {
        "Id": "rule_11"
      },
      {
        "Id": "rule_12"
      }
    ]
  },
  {
    "Id": "68357bf06d966c2c148603a4",
    "Name": "Goblin Warboss",
    "Type": "Profile",
    "BaseId": "4",
    "Children": [
      {
        "Id": "statline_523"
      },
      {
        "Id": "rule_457"
      },
      {
        "Id": "rule_117"
      },
      {
        "Id": "rule_127"
      },
      {
        "Id": "rule_11"
      },
      {
        "Id": "rule_12"
      }
    ]
  },
  {
    "Id": "90fe67d6-05a9-4327-9122-3aede6e22b32",
    "Name": "Goblin Warboss on Goblin Wolf Chariot",
    "Type": "Profile",
    "BaseId": "5",
    "Children": [
      {
        "Id": "statline_523"
      },
      {
        "Id": "statline_515"
      },
      {
        "Id": "statline_516"
      },
      {
        "Id": "statline_517"
      },
      {
        "Id": "rule_457"
      },
      {
        "Id": "rule_25",
        "Info": "(D3+1)"
      },
      {
        "Id": "rule_117"
      },
      {
        "Id": "rule_40"
      },
      {
        "Id": "rule_127"
      },
      {
        "Id": "rule_8"
      },
      {
        "Id": "rule_11"
      },
      {
        "Id": "rule_27"
      },
      {
        "Id": "rule_12"
      },
      {
        "Id": "rule_29"
      },
      {
        "Id": "rule_320"
      }
    ]
  },
  {
    "Id": "9a1b87d3-a8b4-4a38-959a-249a2567110e",
    "Name": "Goblin Warboss on Gigantic Spider",
    "Type": "Profile",
    "BaseId": "6",
    "Children": [
      {
        "Id": "statline_523"
      },
      {
        "Id": "statline_518"
      },
      {
        "Id": "rule_62",
        "Info": "(1)"
      },
      {
        "Id": "rule_33"
      },
      {
        "Id": "rule_457"
      },
      {
        "Id": "rule_117"
      },
      {
        "Id": "rule_5"
      },
      {
        "Id": "rule_78"
      },
      {
        "Id": "rule_127"
      },
      {
        "Id": "rule_8"
      },
      {
        "Id": "rule_11"
      },
      {
        "Id": "rule_12"
      }
    ]
  },
  {
    "Id": "9ce5211d-80a0-4808-944c-e4665ff21817",
    "Name": "Goblin Warboss on Giant Wolf",
    "Type": "Profile",
    "BaseId": "7",
    "Children": [
      {
        "Id": "statline_523"
      },
      {
        "Id": "statline_69"
      },
      {
        "Id": "rule_457"
      },
      {
        "Id": "rule_117"
      },
      {
        "Id": "rule_127"
      },
      {
        "Id": "rule_11"
      },
      {
        "Id": "rule_12"
      }
    ]
  },
  {
    "Id": "68357bf06d966c2c14862752",
    "Name": "Orc Bigboss",
    "Type": "Profile",
    "BaseId": "2",
    "Children": [
      {
        "Id": "statline_524"
      },
      {
        "Id": "rule_121"
      },
      {
        "Id": "rule_124"
      },
      {
        "Id": "rule_130"
      },
      {
        "Id": "rule_117"
      },
      {
        "Id": "rule_127"
      },
      {
        "Id": "rule_129"
      },
      {
        "Id": "rule_11"
      },
      {
        "Id": "rule_12"
      },
      {
        "Id": "rule_47"
      }
    ]
  },
  {
    "Id": "18870958-ce07-4109-a6a7-28dfb5b8875a",
    "Name": "Orc Bigboss on War Boar",
    "Type": "Profile",
    "BaseId": "1",
    "Children": [
      {
        "Id": "statline_524"
      },
      {
        "Id": "statline_56"
      },
      {
        "Id": "rule_62"
      },
      {
        "Id": "rule_121"
      },
      {
        "Id": "rule_122"
      },
      {
        "Id": "rule_124"
      },
      {
        "Id": "rule_130"
      },
      {
        "Id": "rule_117"
      },
      {
        "Id": "rule_127"
      },
      {
        "Id": "rule_8"
      },
      {
        "Id": "rule_128"
      },
      {
        "Id": "rule_129"
      },
      {
        "Id": "rule_11"
      },
      {
        "Id": "rule_12"
      }
    ]
  },
  {
    "Id": "8c27cadd-119e-4689-a433-2332483771ab",
    "Name": "Orc Bigboss on Orc Boar Chariot",
    "Type": "Profile",
    "BaseId": "5",
    "Children": [
      {
        "Id": "statline_524"
      },
      {
        "Id": "statline_57"
      },
      {
        "Id": "statline_58"
      },
      {
        "Id": "statline_59"
      },
      {
        "Id": "rule_121"
      },
      {
        "Id": "rule_22"
      },
      {
        "Id": "rule_23"
      },
      {
        "Id": "rule_124"
      },
      {
        "Id": "rule_130"
      },
      {
        "Id": "rule_25",
        "Info": "(D6+1)"
      },
      {
        "Id": "rule_117"
      },
      {
        "Id": "rule_127"
      },
      {
        "Id": "rule_128"
      },
      {
        "Id": "rule_129"
      },
      {
        "Id": "rule_11"
      },
      {
        "Id": "rule_27"
      },
      {
        "Id": "rule_12"
      },
      {
        "Id": "rule_29"
      }
    ]
  },
  {
    "Id": "68357bf16d966c2c14864727",
    "Name": "Orc Warboss",
    "Type": "Profile",
    "BaseId": "2",
    "Children": [
      {
        "Id": "statline_525"
      },
      {
        "Id": "rule_121"
      },
      {
        "Id": "rule_124"
      },
      {
        "Id": "rule_130"
      },
      {
        "Id": "rule_117"
      },
      {
        "Id": "rule_127"
      },
      {
        "Id": "rule_129"
      },
      {
        "Id": "rule_11"
      },
      {
        "Id": "rule_12"
      },
      {
        "Id": "rule_47"
      }
    ]
  },
  {
    "Id": "5e68e85a-9718-4da6-a049-5452abeab403",
    "Name": "Orc Warboss on War Boar",
    "Type": "Profile",
    "BaseId": "1",
    "Children": [
      {
        "Id": "statline_525"
      },
      {
        "Id": "statline_56"
      },
      {
        "Id": "rule_62"
      },
      {
        "Id": "rule_121"
      },
      {
        "Id": "rule_122"
      },
      {
        "Id": "rule_124"
      },
      {
        "Id": "rule_130"
      },
      {
        "Id": "rule_117"
      },
      {
        "Id": "rule_127"
      },
      {
        "Id": "rule_8"
      },
      {
        "Id": "rule_128"
      },
      {
        "Id": "rule_129"
      },
      {
        "Id": "rule_11"
      },
      {
        "Id": "rule_12"
      }
    ]
  },
  {
    "Id": "d6ba749b-1a63-4de1-8818-fef9b7f4a6fb",
    "Name": "Orc Warboss on Wyvern",
    "Type": "Profile",
    "BaseId": "5",
    "Children": [
      {
        "Id": "statline_525"
      },
      {
        "Id": "statline_63"
      },
      {
        "Id": "rule_121"
      },
      {
        "Id": "rule_22"
      },
      {
        "Id": "rule_51",
        "Info": "(9)"
      },
      {
        "Id": "rule_124"
      },
      {
        "Id": "rule_130"
      },
      {
        "Id": "rule_117"
      },
      {
        "Id": "rule_52"
      },
      {
        "Id": "rule_127"
      },
      {
        "Id": "rule_7",
        "Info": "(D3)"
      },
      {
        "Id": "rule_8"
      },
      {
        "Id": "rule_54"
      },
      {
        "Id": "rule_129"
      },
      {
        "Id": "rule_11"
      },
      {
        "Id": "rule_38"
      },
      {
        "Id": "rule_132"
      },
      {
        "Id": "rule_133"
      }
    ]
  },
  {
    "Id": "22341030-f36d-41fd-8375-ce4ca271048d",
    "Name": "Orc Warboss on Orc Boar Chariot",
    "Type": "Profile",
    "BaseId": "5",
    "Children": [
      {
        "Id": "statline_525"
      },
      {
        "Id": "statline_57"
      },
      {
        "Id": "statline_58"
      },
      {
        "Id": "statline_59"
      },
      {
        "Id": "rule_121"
      },
      {
        "Id": "rule_22"
      },
      {
        "Id": "rule_23"
      },
      {
        "Id": "rule_124"
      },
      {
        "Id": "rule_130"
      },
      {
        "Id": "rule_25",
        "Info": "(D6+1)"
      },
      {
        "Id": "rule_117"
      },
      {
        "Id": "rule_127"
      },
      {
        "Id": "rule_128"
      },
      {
        "Id": "rule_129"
      },
      {
        "Id": "rule_11"
      },
      {
        "Id": "rule_27"
      },
      {
        "Id": "rule_12"
      },
      {
        "Id": "rule_29"
      }
    ]
  },
  {
    "Id": "68357bf26d966c2c14866b55",
    "Name": "Orc Weirdboy",
    "Type": "Profile",
    "BaseId": "2",
    "Children": [
      {
        "Id": "statline_526"
      },
      {
        "Id": "rule_121"
      },
      {
        "Id": "rule_130"
      },
      {
        "Id": "rule_472"
      },
      {
        "Id": "rule_473"
      },
      {
        "Id": "rule_11"
      },
      {
        "Id": "rule_183"
      },
      {
        "Id": "rule_12"
      },
      {
        "Id": "rule_474"
      }
    ]
  },
  {
    "Id": "8900ab60-6e54-4729-80ff-b957d155d3bf",
    "Name": "Orc Weirdboy on War Boar",
    "Type": "Profile",
    "BaseId": "1",
    "Children": [
      {
        "Id": "statline_526"
      },
      {
        "Id": "statline_56"
      },
      {
        "Id": "rule_62"
      },
      {
        "Id": "rule_121"
      },
      {
        "Id": "rule_122"
      },
      {
        "Id": "rule_130"
      },
      {
        "Id": "rule_472"
      },
      {
        "Id": "rule_473"
      },
      {
        "Id": "rule_8"
      },
      {
        "Id": "rule_128"
      },
      {
        "Id": "rule_11"
      },
      {
        "Id": "rule_12"
      }
    ]
  },
  {
    "Id": "68357bf26d966c2c14867f3a",
    "Name": "Orc Weirdnob",
    "Type": "Profile",
    "BaseId": "2",
    "Children": [
      {
        "Id": "statline_527"
      },
      {
        "Id": "rule_121"
      },
      {
        "Id": "rule_130"
      },
      {
        "Id": "rule_472"
      },
      {
        "Id": "rule_473"
      },
      {
        "Id": "rule_11"
      },
      {
        "Id": "rule_183"
      },
      {
        "Id": "rule_12"
      },
      {
        "Id": "rule_474"
      }
    ]
  },
  {
    "Id": "4757b2f8-b902-4d5a-9f0f-f299337ced66",
    "Name": "Orc Weirdnob on War Boar",
    "Type": "Profile",
    "BaseId": "1",
    "Children": [
      {
        "Id": "statline_527"
      },
      {
        "Id": "statline_56"
      },
      {
        "Id": "rule_62"
      },
      {
        "Id": "rule_121"
      },
      {
        "Id": "rule_122"
      },
      {
        "Id": "rule_130"
      },
      {
        "Id": "rule_472"
      },
      {
        "Id": "rule_473"
      },
      {
        "Id": "rule_8"
      },
      {
        "Id": "rule_128"
      },
      {
        "Id": "rule_11"
      },
      {
        "Id": "rule_12"
      }
    ]
  },
  {
    "Id": "2bbd3c36-f0df-411d-a7e5-3307325b9b7d",
    "Name": "Orc Weirdnob on Wyvern",
    "Type": "Profile",
    "BaseId": "5",
    "Children": [
      {
        "Id": "statline_527"
      },
      {
        "Id": "statline_63"
      },
      {
        "Id": "rule_121"
      },
      {
        "Id": "rule_22"
      },
      {
        "Id": "rule_51",
        "Info": "(9)"
      },
      {
        "Id": "rule_130"
      },
      {
        "Id": "rule_52"
      },
      {
        "Id": "rule_472"
      },
      {
        "Id": "rule_473"
      },
      {
        "Id": "rule_7",
        "Info": "(D3)"
      },
      {
        "Id": "rule_8"
      },
      {
        "Id": "rule_54"
      },
      {
        "Id": "rule_11"
      },
      {
        "Id": "rule_38"
      },
      {
        "Id": "rule_132"
      },
      {
        "Id": "rule_133"
      }
    ]
  },
  {
    "Id": "68357bf36d966c2c14869d40",
    "Name": "Troll Hag",
    "Type": "Profile",
    "BaseId": "10",
    "Children": [
      {
        "Id": "statline_537"
      },
      {
        "Id": "rule_22"
      },
      {
        "Id": "rule_90"
      },
      {
        "Id": "rule_57"
      },
      {
        "Id": "rule_481"
      },
      {
        "Id": "rule_52"
      },
      {
        "Id": "rule_482"
      },
      {
        "Id": "rule_66",
        "Info": "(5+)"
      },
      {
        "Id": "rule_483"
      },
      {
        "Id": "rule_7",
        "Info": "(D6)"
      },
      {
        "Id": "rule_91"
      },
      {
        "Id": "rule_54"
      },
      {
        "Id": "rule_60"
      },
      {
        "Id": "rule_86"
      },
      {
        "Id": "rule_183"
      },
      {
        "Id": "rule_12"
      },
      {
        "Id": "rule_38"
      },
      {
        "Id": "rule_484"
      },
      {
        "Id": "rule_485"
      }
    ]
  },
  {
    "Id": "68357bf36d966c2c1486a728",
    "Name": "Common Troll",
    "Type": "Profile",
    "BaseId": "9",
    "Children": [
      {
        "Id": "statline_538"
      },
      {
        "Id": "rule_30",
        "Info": "(1)"
      },
      {
        "Id": "rule_22"
      },
      {
        "Id": "rule_31"
      },
      {
        "Id": "rule_90"
      },
      {
        "Id": "rule_66",
        "Info": "(5+)"
      },
      {
        "Id": "rule_91"
      },
      {
        "Id": "rule_12"
      },
      {
        "Id": "rule_47"
      },
      {
        "Id": "rule_92"
      }
    ]
  },
  {
    "Id": "68357bf46d966c2c1486a982",
    "Name": "Goblin",
    "Type": "Profile",
    "BaseId": "4",
    "Children": [
      {
        "Id": "statline_539"
      },
      {
        "Id": "rule_22"
      },
      {
        "Id": "rule_457"
      },
      {
        "Id": "rule_42"
      },
      {
        "Id": "rule_117"
      },
      {
        "Id": "rule_11"
      },
      {
        "Id": "rule_12"
      },
      {
        "Id": "rule_49"
      }
    ]
  },
  {
    "Id": "68357bd76d966c2c148290f4c",
    "Name": "Boss (Goblin)",
    "Type": "Profile",
    "BaseId": "4",
    "Children": [
      {
        "Id": "statline_540"
      },
      {
        "Id": "rule_22"
      },
      {
        "Id": "rule_457"
      },
      {
        "Id": "rule_42"
      },
      {
        "Id": "rule_117"
      },
      {
        "Id": "rule_11"
      },
      {
        "Id": "rule_37"
      }
    ]
  },
  {
    "Id": "68357bf46d966c2c1486b38e",
    "Name": "Spider Rider",
    "Type": "Profile",
    "BaseId": "7",
    "Children": [
      {
        "Id": "statline_541"
      },
      {
        "Id": "statline_542"
      },
      {
        "Id": "rule_33"
      },
      {
        "Id": "rule_457"
      },
      {
        "Id": "rule_117"
      },
      {
        "Id": "rule_5"
      },
      {
        "Id": "rule_40"
      },
      {
        "Id": "rule_78"
      },
      {
        "Id": "rule_8"
      },
      {
        "Id": "rule_11"
      },
      {
        "Id": "rule_12"
      },
      {
        "Id": "rule_49"
      }
    ]
  },
  {
    "Id": "68357bd76d966c2c14829c88c",
    "Name": "Boss (Spider Rider)",
    "Type": "Profile",
    "BaseId": "7",
    "Children": [
      {
        "Id": "statline_531"
      },
      {
        "Id": "statline_542"
      },
      {
        "Id": "rule_33"
      },
      {
        "Id": "rule_457"
      },
      {
        "Id": "rule_117"
      },
      {
        "Id": "rule_5"
      },
      {
        "Id": "rule_40"
      },
      {
        "Id": "rule_78"
      },
      {
        "Id": "rule_8"
      },
      {
        "Id": "rule_11"
      },
      {
        "Id": "rule_37"
      }
    ]
  },
  {
    "Id": "68357bf46d966c2c1486bd8e",
    "Name": "Wolf Rider",
    "Type": "Profile",
    "BaseId": "7",
    "Children": [
      {
        "Id": "statline_530"
      },
      {
        "Id": "statline_69"
      },
      {
        "Id": "rule_48"
      },
      {
        "Id": "rule_33"
      },
      {
        "Id": "rule_457"
      },
      {
        "Id": "rule_146"
      },
      {
        "Id": "rule_117"
      },
      {
        "Id": "rule_40"
      },
      {
        "Id": "rule_43"
      },
      {
        "Id": "rule_8"
      },
      {
        "Id": "rule_11"
      },
      {
        "Id": "rule_12"
      },
      {
        "Id": "rule_49"
      }
    ]
  },
  {
    "Id": "68357bd76d966c2c1482a810c",
    "Name": "Boss (Wolf Rider)",
    "Type": "Profile",
    "BaseId": "7",
    "Children": [
      {
        "Id": "statline_531"
      },
      {
        "Id": "statline_69"
      },
      {
        "Id": "rule_48"
      },
      {
        "Id": "rule_33"
      },
      {
        "Id": "rule_457"
      },
      {
        "Id": "rule_146"
      },
      {
        "Id": "rule_117"
      },
      {
        "Id": "rule_40"
      },
      {
        "Id": "rule_43"
      },
      {
        "Id": "rule_8"
      },
      {
        "Id": "rule_37"
      }
    ]
  },
  {
    "Id": "68357bf56d966c2c1486c80e",
    "Name": "Orc Boy",
    "Type": "Profile",
    "BaseId": "2",
    "Children": [
      {
        "Id": "statline_543"
      },
      {
        "Id": "rule_121"
      },
      {
        "Id": "rule_22"
      },
      {
        "Id": "rule_65"
      },
      {
        "Id": "rule_130"
      },
      {
        "Id": "rule_117"
      },
      {
        "Id": "rule_11"
      },
      {
        "Id": "rule_12"
      }
    ]
  },
  {
    "Id": "68357bf56d966c2c1486eae5",
    "Name": "River Troll",
    "Type": "Profile",
    "BaseId": "9",
    "Children": [
      {
        "Id": "statline_544"
      },
      {
        "Id": "rule_30",
        "Info": "(1)"
      },
      {
        "Id": "rule_22"
      },
      {
        "Id": "rule_31"
      },
      {
        "Id": "rule_90"
      },
      {
        "Id": "rule_66",
        "Info": "(5+)"
      },
      {
        "Id": "rule_91"
      },
      {
        "Id": "rule_12"
      },
      {
        "Id": "rule_47"
      },
      {
        "Id": "rule_92"
      }
    ]
  },
  {
    "Id": "68357bf56d966c2c1486ed4e",
    "Name": "Stone Troll",
    "Type": "Profile",
    "BaseId": "9",
    "Children": [
      {
        "Id": "statline_545"
      },
      {
        "Id": "rule_30",
        "Info": "(1)"
      },
      {
        "Id": "rule_62",
        "Info": "(1)"
      },
      {
        "Id": "rule_22"
      },
      {
        "Id": "rule_31"
      },
      {
        "Id": "rule_90"
      },
      {
        "Id": "rule_105",
        "Info": "(-1)"
      },
      {
        "Id": "rule_66",
        "Info": "(5+)"
      },
      {
        "Id": "rule_91"
      },
      {
        "Id": "rule_12"
      },
      {
        "Id": "rule_47"
      },
      {
        "Id": "rule_92"
      }
    ]
  },
  {
    "Id": "68357bf66d966c2c1486f208",
    "Name": "Goblin Wolf Chariot",
    "Type": "Profile",
    "BaseId": "5",
    "Children": [
      {
        "Id": "statline_529"
      },
      {
        "Id": "statline_516"
      },
      {
        "Id": "statline_517"
      },
      {
        "Id": "rule_457"
      },
      {
        "Id": "rule_25",
        "Info": "(D3+1)"
      },
      {
        "Id": "rule_117"
      },
      {
        "Id": "rule_40"
      },
      {
        "Id": "rule_8"
      },
      {
        "Id": "rule_11"
      },
      {
        "Id": "rule_27"
      },
      {
        "Id": "rule_12"
      },
      {
        "Id": "rule_29"
      },
      {
        "Id": "rule_320"
      }
    ]
  },
  {
    "Id": "68357bf66d966c2c1486f73f",
    "Name": "Boar Boy",
    "Type": "Profile",
    "BaseId": "1",
    "Children": [
      {
        "Id": "statline_532"
      },
      {
        "Id": "statline_56"
      },
      {
        "Id": "rule_62",
        "Info": "(1)"
      },
      {
        "Id": "rule_121"
      },
      {
        "Id": "rule_22"
      },
      {
        "Id": "rule_122"
      },
      {
        "Id": "rule_124"
      },
      {
        "Id": "rule_130"
      },
      {
        "Id": "rule_117"
      },
      {
        "Id": "rule_8"
      },
      {
        "Id": "rule_128"
      },
      {
        "Id": "rule_11"
      },
      {
        "Id": "rule_12"
      },
      {
        "Id": "rule_47"
      }
    ]
  },
  {
    "Id": "68357bd86d966c2c1482c25ac",
    "Name": "Boss (Orc)",
    "Type": "Profile",
    "BaseId": "2",
    "Children": [
      {
        "Id": "statline_546"
      },
      {
        "Id": "rule_121"
      },
      {
        "Id": "rule_22"
      },
      {
        "Id": "rule_65"
      },
      {
        "Id": "rule_130"
      },
      {
        "Id": "rule_117"
      },
      {
        "Id": "rule_11"
      },
      {
        "Id": "rule_37"
      }
    ]
  },
  {
    "Id": "68357bf76d966c2c14871a8b",
    "Name": "Orc Boar Chariot",
    "Type": "Profile",
    "BaseId": "5",
    "Children": [
      {
        "Id": "statline_534"
      },
      {
        "Id": "statline_58"
      },
      {
        "Id": "statline_59"
      },
      {
        "Id": "rule_121"
      },
      {
        "Id": "rule_22"
      },
      {
        "Id": "rule_23"
      },
      {
        "Id": "rule_130"
      },
      {
        "Id": "rule_25",
        "Info": "(D6+1)"
      },
      {
        "Id": "rule_117"
      },
      {
        "Id": "rule_128"
      },
      {
        "Id": "rule_11"
      },
      {
        "Id": "rule_27"
      },
      {
        "Id": "rule_12"
      },
      {
        "Id": "rule_29"
      }
    ]
  },
  {
    "Id": "68357bf76d966c2c148721c6",
    "Name": "Giant",
    "Type": "Profile",
    "BaseId": "6",
    "Children": [
      {
        "Id": "statline_505"
      },
      {
        "Id": "rule_22"
      },
      {
        "Id": "rule_84"
      },
      {
        "Id": "rule_57"
      },
      {
        "Id": "rule_52"
      },
      {
        "Id": "rule_477"
      },
      {
        "Id": "rule_7",
        "Info": "(D6)"
      },
      {
        "Id": "rule_54"
      },
      {
        "Id": "rule_60"
      },
      {
        "Id": "rule_86"
      },
      {
        "Id": "rule_87"
      },
      {
        "Id": "rule_47"
      }
    ]
  },
  {
    "Id": "68357bf76d966c2c1487242d",
    "Name": "Ogre",
    "Type": "Profile",
    "BaseId": "9",
    "Children": [
      {
        "Id": "statline_45"
      },
      {
        "Id": "rule_30",
        "Info": "(1)"
      },
      {
        "Id": "rule_22"
      },
      {
        "Id": "rule_31"
      },
      {
        "Id": "rule_25",
        "Info": "(1)"
      },
      {
        "Id": "rule_96"
      },
      {
        "Id": "rule_46"
      },
      {
        "Id": "rule_97"
      },
      {
        "Id": "rule_12"
      },
      {
        "Id": "rule_47"
      }
    ]
  },
  {
    "Id": "68357bf76d966c2c14872a0d",
    "Name": "Champion (Ogre)",
    "Type": "Profile",
    "BaseId": "9",
    "Children": [
      {
        "Id": "statline_46"
      },
      {
        "Id": "rule_30",
        "Info": "(1)"
      },
      {
        "Id": "rule_22"
      },
      {
        "Id": "rule_31"
      },
      {
        "Id": "rule_25",
        "Info": "(1)"
      },
      {
        "Id": "rule_96"
      },
      {
        "Id": "rule_46"
      },
      {
        "Id": "rule_97"
      },
      {
        "Id": "rule_37"
      },
      {
        "Id": "rule_12"
      },
      {
        "Id": "rule_47"
      }
    ]
  },
  {
    "Id": "68357bf86d966c2c148736a6",
    "Name": "Bonegrinder Giant",
    "Type": "Profile",
    "BaseId": "5",
    "Children": [
      {
        "Id": "statline_48"
      },
      {
        "Id": "rule_98"
      },
      {
        "Id": "rule_22"
      },
      {
        "Id": "rule_57"
      },
      {
        "Id": "rule_52"
      },
      {
        "Id": "rule_96"
      },
      {
        "Id": "rule_7",
        "Info": "(D6+1)"
      },
      {
        "Id": "rule_54"
      },
      {
        "Id": "rule_60"
      },
      {
        "Id": "rule_86"
      },
      {
        "Id": "rule_99"
      },
      {
        "Id": "rule_47"
      }
    ]
  },
  {
    "Id": "68357bf86d966c2c148738f7",
    "Name": "Doomseeker",
    "Type": "Profile",
    "BaseId": "4",
    "Children": [
      {
        "Id": "statline_100"
      },
      {
        "Id": "rule_100"
      },
      {
        "Id": "rule_101"
      },
      {
        "Id": "rule_102"
      },
      {
        "Id": "rule_103"
      },
      {
        "Id": "rule_104",
        "Info": "(Orcs & Goblins)"
      },
      {
        "Id": "rule_57"
      },
      {
        "Id": "rule_25",
        "Info": "(D3+1)"
      },
      {
        "Id": "rule_39"
      },
      {
        "Id": "rule_105",
        "Info": "(-2)"
      },
      {
        "Id": "rule_96"
      },
      {
        "Id": "rule_88"
      },
      {
        "Id": "rule_106"
      },
      {
        "Id": "rule_86"
      },
      {
        "Id": "rule_107"
      },
      {
        "Id": "rule_108"
      },
      {
        "Id": "rule_12"
      }
    ]
  },
  {
    "Id": "68357bf86d966c2c14873b99",
    "Name": "Imperial Dwarf Warrior",
    "Type": "Profile",
    "BaseId": "4",
    "Children": [
      {
        "Id": "statline_208"
      },
      {
        "Id": "rule_22"
      },
      {
        "Id": "rule_104",
        "Info": "(Orcs & Goblins)"
      },
      {
        "Id": "rule_105",
        "Info": "(-1)"
      },
      {
        "Id": "rule_96"
      },
      {
        "Id": "rule_106"
      },
      {
        "Id": "rule_109"
      },
      {
        "Id": "rule_12"
      },
      {
        "Id": "rule_47"
      }
    ]
  },
  {
    "Id": "68357bf96d966c2c148746c3",
    "Name": "Imperial Ogre",
    "Type": "Profile",
    "BaseId": "9",
    "Children": [
      {
        "Id": "statline_258"
      },
      {
        "Id": "rule_30",
        "Info": "(1)"
      },
      {
        "Id": "rule_22"
      },
      {
        "Id": "rule_31"
      },
      {
        "Id": "rule_25",
        "Info": "(1)"
      },
      {
        "Id": "rule_96"
      },
      {
        "Id": "rule_46"
      },
      {
        "Id": "rule_97"
      },
      {
        "Id": "rule_12"
      },
      {
        "Id": "rule_47"
      }
    ]
  },
  {
    "Id": "68357bf96d966c2c14874952",
    "Name": "Champion (Imperial Ogre)",
    "Type": "Profile",
    "BaseId": "9",
    "Children": [
      {
        "Id": "statline_259"
      },
      {
        "Id": "rule_30",
        "Info": "(1)"
      },
      {
        "Id": "rule_22"
      },
      {
        "Id": "rule_31"
      },
      {
        "Id": "rule_25",
        "Info": "(1)"
      },
      {
        "Id": "rule_96"
      },
      {
        "Id": "rule_46"
      },
      {
        "Id": "rule_97"
      },
      {
        "Id": "rule_37"
      },
      {
        "Id": "rule_12"
      },
      {
        "Id": "rule_47"
      }
    ]
  },
  {
    "Id": "68357bf96d966c2c14874bc1",
    "Name": "Standard Bearer (Dragon Company trooper)",
    "Type": "Profile",
    "BaseId": "4",
    "Children": [
      {
        "Id": "statline_293"
      },
      {
        "Id": "rule_22"
      },
      {
        "Id": "rule_110"
      },
      {
        "Id": "rule_103"
      },
      {
        "Id": "rule_104",
        "Info": "(Orcs & Goblins)"
      },
      {
        "Id": "rule_105",
        "Info": "(-1)"
      },
      {
        "Id": "rule_96"
      },
      {
        "Id": "rule_106"
      },
      {
        "Id": "rule_59"
      },
      {
        "Id": "rule_111"
      },
      {
        "Id": "rule_12"
      },
      {
        "Id": "rule_47"
      },
      {
        "Id": "rule_49"
      },
      {
        "Id": "rule_112"
      }
    ]
  }
]