[
  {
    "Id": "unit_1188",
    "Name": "Winged Warsphinx",
    "Attributes": {
      "totalCost": "0",
      "height": "Standard"
    },
    "BasicProfileIds": [
      "profile_1765312756660"
    ],
    "DefaultFront": 1,
    "Formation": 1
  },
  {
    "Id": "unit_1189",
    "Name": "Nekaph",
    "Attributes": {
      "totalCost": "120",
      "height": "Standard"
    },
    "BasicProfileIds": [
      "68357c426d966c2c1497884d"
    ],
    "DefaultFront": 1,
    "Formation": 1
  },
  {
    "Id": "unit_1190",
    "Name": "Prince Apophas",
    "Attributes": {
      "totalCost": "130",
      "height": "Standard"
    },
    "BasicProfileIds": [
      "68357c426d966c2c1497a759"
    ],
    "DefaultFront": 1,
    "Formation": 1
  },
  {
    "Id": "unit_1191",
    "Name": "Settra the Imperishable",
    "Attributes": {
      "totalCost": "445",
      "height": "Standard"
    },
    "BasicProfileIds": [
      "68357c436d966c2c1497c667"
    ],
    "DefaultFront": 1,
    "Formation": 1
  },
  {
    "Id": "unit_1192",
    "Name": "High Priest",
    "Attributes": {
      "totalCost": "140",
      "height": "Standard"
    },
    "BasicProfileIds": [
      "68357c446d966c2c149804d9"
    ],
    "DefaultFront": 1,
    "Formation": 1
  },
  {
    "Id": "unit_1193",
    "Name": "High Priest on Skeletal Steed",
    "Attributes": {
      "totalCost": "152",
      "height": "Standard"
    },
    "BasicProfileIds": [
      "ba9a09a0-db04-4abb-86dd-aaef5422f5ec"
    ],
    "DefaultFront": 1,
    "Formation": 1
  },
  {
    "Id": "unit_1194",
    "Name": "High Priest on Necrolith Bone Dragon",
    "Attributes": {
      "totalCost": "335",
      "height": "Standard"
    },
    "BasicProfileIds": [
      "d4a3aa9c-420e-4025-ae34-3356914279c3"
    ],
    "DefaultFront": 1,
    "Formation": 1
  },
  {
    "Id": "unit_1195",
    "Name": "High Priest on Barded Skeletal Steed",
    "Attributes": {
      "totalCost": "0",
      "height": "Standard"
    },
    "BasicProfileIds": [
      "profile_1765311714447"
    ],
    "DefaultFront": 1,
    "Formation": 1
  },
  {
    "Id": "unit_1196",
    "Name": "Mortuary Priest",
    "Attributes": {
      "totalCost": "55",
      "height": "Standard"
    },
    "BasicProfileIds": [
      "68357c456d966c2c149878d0"
    ],
    "DefaultFront": 1,
    "Formation": 1
  },
  {
    "Id": "unit_1197",
    "Name": "Mortuary Priest on Skeletal Steed",
    "Attributes": {
      "totalCost": "67",
      "height": "Standard"
    },
    "BasicProfileIds": [
      "1c9b91d7-ae27-4e14-827d-0d3412751075"
    ],
    "DefaultFront": 1,
    "Formation": 1
  },
  {
    "Id": "unit_1198",
    "Name": "Mortuary Priest on Barded Skeletal Steed",
    "Attributes": {
      "totalCost": "0",
      "height": "Standard"
    },
    "BasicProfileIds": [
      "profile_1765311714447"
    ],
    "DefaultFront": 1,
    "Formation": 1
  },
  {
    "Id": "unit_1199",
    "Name": "Necrotect",
    "Attributes": {
      "totalCost": "55",
      "height": "Standard"
    },
    "BasicProfileIds": [
      "68357c466d966c2c1498c935"
    ],
    "DefaultFront": 1,
    "Formation": 1
  },
  {
    "Id": "unit_1200",
    "Name": "Royal Herald",
    "Attributes": {
      "totalCost": "60",
      "height": "Standard"
    },
    "BasicProfileIds": [
      "68357c476d966c2c1498ee6e"
    ],
    "DefaultFront": 1,
    "Formation": 1
  },
  {
    "Id": "unit_1201",
    "Name": "Royal Herald on Skeletal Steed",
    "Attributes": {
      "totalCost": "72",
      "height": "Standard"
    },
    "BasicProfileIds": [
      "3a2149b4-2f3b-4d43-8f10-aaf34e422066"
    ],
    "DefaultFront": 1,
    "Formation": 1
  },
  {
    "Id": "unit_1202",
    "Name": "Royal Herald on Skeleton Chariot",
    "Attributes": {
      "totalCost": "95",
      "height": "Standard"
    },
    "BasicProfileIds": [
      "65701982-cc53-42a8-88ce-2139ec95d01e"
    ],
    "DefaultFront": 1,
    "Formation": 1
  },
  {
    "Id": "unit_1203",
    "Name": "Royal Herald on Barded Skeletal Steed",
    "Attributes": {
      "totalCost": "0",
      "height": "Standard"
    },
    "BasicProfileIds": [
      "profile_1765311714447"
    ],
    "DefaultFront": 1,
    "Formation": 1
  },
  {
    "Id": "unit_1204",
    "Name": "Tomb King",
    "Attributes": {
      "totalCost": "160",
      "height": "Standard"
    },
    "BasicProfileIds": [
      "68357c486d966c2c149963b6"
    ],
    "DefaultFront": 1,
    "Formation": 1
  },
  {
    "Id": "unit_1205",
    "Name": "Tomb King on Skeletal Steed",
    "Attributes": {
      "totalCost": "172",
      "height": "Standard"
    },
    "BasicProfileIds": [
      "61286aad-3e33-4d70-9186-54adc725642f"
    ],
    "DefaultFront": 1,
    "Formation": 1
  },
  {
    "Id": "unit_1206",
    "Name": "Tomb King on Skeleton Chariot",
    "Attributes": {
      "totalCost": "195",
      "height": "Standard"
    },
    "BasicProfileIds": [
      "8a7e9dec-e17b-4d11-8e41-2288995f3874"
    ],
    "DefaultFront": 1,
    "Formation": 1
  },
  {
    "Id": "unit_1207",
    "Name": "Tomb King on Necrolith Bone Dragon",
    "Attributes": {
      "totalCost": "355",
      "height": "Standard"
    },
    "BasicProfileIds": [
      "8975afd7-61b1-42b6-913f-a668e22db93f"
    ],
    "DefaultFront": 1,
    "Formation": 1
  },
  {
    "Id": "unit_1208",
    "Name": "Tomb King on Khemrian Warsphinx",
    "Attributes": {
      "totalCost": "335",
      "height": "Standard"
    },
    "BasicProfileIds": [
      "66457e07-ca13-499d-b683-727cbcf57a72"
    ],
    "DefaultFront": 1,
    "Formation": 1
  },
  {
    "Id": "unit_1209",
    "Name": "Tomb King on Barded Skeletal Steed",
    "Attributes": {
      "totalCost": "0",
      "height": "Standard"
    },
    "BasicProfileIds": [
      "profile_1765311714447"
    ],
    "DefaultFront": 1,
    "Formation": 1
  },
  {
    "Id": "unit_1210",
    "Name": "Tomb Prince",
    "Attributes": {
      "totalCost": "90",
      "height": "Standard"
    },
    "BasicProfileIds": [
      "68357c4a6d966c2c149a20cc"
    ],
    "DefaultFront": 1,
    "Formation": 1
  },
  {
    "Id": "unit_1211",
    "Name": "Tomb Prince on Skeletal Steed",
    "Attributes": {
      "totalCost": "102",
      "height": "Standard"
    },
    "BasicProfileIds": [
      "108dd568-91cd-4bd7-8421-4fedf57a5875"
    ],
    "DefaultFront": 1,
    "Formation": 1
  },
  {
    "Id": "unit_1212",
    "Name": "Tomb Prince on Skeleton Chariot",
    "Attributes": {
      "totalCost": "125",
      "height": "Standard"
    },
    "BasicProfileIds": [
      "88fb6f8e-1b58-40bd-9bd1-6ee527f6cd04"
    ],
    "DefaultFront": 1,
    "Formation": 1
  },
  {
    "Id": "unit_1213",
    "Name": "Tomb Prince on Barded Skeletal Steed",
    "Attributes": {
      "totalCost": "0",
      "height": "Standard"
    },
    "BasicProfileIds": [
      "profile_1765311714447"
    ],
    "DefaultFront": 1,
    "Formation": 1
  },
  {
    "Id": "unit_1214",
    "Name": "Sepulchral Stalkers",
    "Attributes": {
      "totalCost": "52",
      "height": "Standard"
    },
    "BasicProfileIds": [
      "68357c4b6d966c2c149a9157"
    ],
    "DefaultFront": 3,
    "Formation": 1
  },
  {
    "Id": "unit_1215",
    "Name": "Skeleton Archers",
    "Attributes": {
      "totalCost": "5",
      "height": "Standard"
    },
    "BasicProfileIds": [
      "68357c4c6d966c2c149ab074"
    ],
    "DefaultFront": 5,
    "Formation": 1
  },
  {
    "Id": "unit_1216",
    "Name": "Skeleton Chariots",
    "Attributes": {
      "totalCost": "43",
      "height": "Standard"
    },
    "BasicProfileIds": [
      "68357c4d6d966c2c149b2cdd"
    ],
    "DefaultFront": 3,
    "Formation": 1
  },
  {
    "Id": "unit_1217",
    "Name": "Skeleton Horse Archers",
    "Attributes": {
      "totalCost": "11",
      "height": "Standard"
    },
    "BasicProfileIds": [
      "68357c4f6d966c2c149bc8f5"
    ],
    "DefaultFront": 5,
    "Formation": 1
  },
  {
    "Id": "unit_1218",
    "Name": "Skeleton Horsemen",
    "Attributes": {
      "totalCost": "11",
      "height": "Standard"
    },
    "BasicProfileIds": [
      "68357c506d966c2c149c459d"
    ],
    "DefaultFront": 5,
    "Formation": 1
  },
  {
    "Id": "unit_1219",
    "Name": "Skeleton Skirmishers",
    "Attributes": {
      "totalCost": "4",
      "height": "Standard"
    },
    "BasicProfileIds": [
      "68357c516d966c2c149cdb4d"
    ],
    "DefaultFront": 5,
    "Formation": 1
  },
  {
    "Id": "unit_1220",
    "Name": "Skeleton Warriors",
    "Attributes": {
      "totalCost": "4",
      "height": "Standard"
    },
    "BasicProfileIds": [
      "68357c526d966c2c149cfa66"
    ],
    "DefaultFront": 5,
    "Formation": 1
  },
  {
    "Id": "unit_1221",
    "Name": "Tomb Guard",
    "Attributes": {
      "totalCost": "10",
      "height": "Standard"
    },
    "BasicProfileIds": [
      "68357c536d966c2c149d8fc2"
    ],
    "DefaultFront": 5,
    "Formation": 1
  },
  {
    "Id": "unit_1222",
    "Name": "Tomb Swarms",
    "Attributes": {
      "totalCost": "37",
      "height": "Standard"
    },
    "BasicProfileIds": [
      "68357c556d966c2c149e2b8c"
    ],
    "DefaultFront": 3,
    "Formation": 1
  },
  {
    "Id": "unit_1223",
    "Name": "Carrion",
    "Attributes": {
      "totalCost": "27",
      "height": "Standard"
    },
    "BasicProfileIds": [
      "68357c556d966c2c149e4a8e"
    ],
    "DefaultFront": 3,
    "Formation": 1
  },
  {
    "Id": "unit_1224",
    "Name": "Khemrian Warsphinx",
    "Attributes": {
      "totalCost": "175",
      "height": "Standard"
    },
    "BasicProfileIds": [
      "68357c556d966c2c149e6991"
    ],
    "DefaultFront": 1,
    "Formation": 1
  },
  {
    "Id": "unit_1225",
    "Name": "Necropolis Knights",
    "Attributes": {
      "totalCost": "54",
      "height": "Standard"
    },
    "BasicProfileIds": [
      "68357c566d966c2c149e88be"
    ],
    "DefaultFront": 3,
    "Formation": 1
  },
  {
    "Id": "unit_1226",
    "Name": "Sepulchral Stalkers",
    "Attributes": {
      "totalCost": "52",
      "height": "Standard"
    },
    "BasicProfileIds": [
      "68357c586d966c2c149f24ce"
    ],
    "DefaultFront": 3,
    "Formation": 1
  },
  {
    "Id": "unit_1227",
    "Name": "Tomb Guard",
    "Attributes": {
      "totalCost": "10",
      "height": "Standard"
    },
    "BasicProfileIds": [
      "68357c586d966c2c149f43e8"
    ],
    "DefaultFront": 5,
    "Formation": 1
  },
  {
    "Id": "unit_1228",
    "Name": "Tomb Scorpion",
    "Attributes": {
      "totalCost": "70",
      "height": "Standard"
    },
    "BasicProfileIds": [
      "68357c5a6d966c2c149fdfb1"
    ],
    "DefaultFront": 1,
    "Formation": 1
  },
  {
    "Id": "unit_1229",
    "Name": "Ushabti",
    "Attributes": {
      "totalCost": "49",
      "height": "Standard"
    },
    "BasicProfileIds": [
      "68357c5a6d966c2c149ffec1"
    ],
    "DefaultFront": 3,
    "Formation": 1
  },
  {
    "Id": "unit_1230",
    "Name": "Casket of Souls",
    "Attributes": {
      "totalCost": "135",
      "height": "Standard"
    },
    "BasicProfileIds": [
      "68357c5b6d966c2c14a03ceb"
    ],
    "DefaultFront": 1,
    "Formation": 1
  },
  {
    "Id": "unit_1231",
    "Name": "Necrolith Colossus",
    "Attributes": {
      "totalCost": "160",
      "height": "Standard"
    },
    "BasicProfileIds": [
      "68357c5b6d966c2c14a05bf8"
    ],
    "DefaultFront": 1,
    "Formation": 1
  },
  {
    "Id": "unit_1232",
    "Name": "Necrosphinx",
    "Attributes": {
      "totalCost": "195",
      "height": "Standard"
    },
    "BasicProfileIds": [
      "68357c5c6d966c2c14a07afc"
    ],
    "DefaultFront": 1,
    "Formation": 1
  },
  {
    "Id": "unit_1233",
    "Name": "Screaming Skull Catapult",
    "Attributes": {
      "totalCost": "105",
      "height": "Standard"
    },
    "BasicProfileIds": [
      "68357c5c6d966c2c14a09a0d"
    ],
    "DefaultFront": 1,
    "Formation": 1
  },
  {
    "Id": "unit_1234",
    "Name": "Badlands Ogre Bulls",
    "Attributes": {
      "totalCost": "31",
      "height": "Standard"
    },
    "BasicProfileIds": [
      "68357c5c6d966c2c14a0b939"
    ],
    "DefaultFront": 3,
    "Formation": 1
  },
  {
    "Id": "unit_1235",
    "Name": "Bonegrinder Giant",
    "Attributes": {
      "totalCost": "300",
      "height": "Standard"
    },
    "BasicProfileIds": [
      "68357c5e6d966c2c14a13e93"
    ],
    "DefaultFront": 1,
    "Formation": 1
  },
  {
    "Id": "unit_1236",
    "Name": "Doomseeker",
    "Attributes": {
      "totalCost": "50",
      "height": "Standard"
    },
    "BasicProfileIds": [
      "68357c5e6d966c2c14a15d9b"
    ],
    "DefaultFront": 1,
    "Formation": 1
  },
  {
    "Id": "unit_1237",
    "Name": "Imperial Dwarf Mercenaries",
    "Attributes": {
      "totalCost": "8",
      "height": "Standard"
    },
    "BasicProfileIds": [
      "68357c5e6d966c2c14a17cf5"
    ],
    "DefaultFront": 5,
    "Formation": 1
  },
  {
    "Id": "unit_1238",
    "Name": "Imperial Ogres",
    "Attributes": {
      "totalCost": "31",
      "height": "Standard"
    },
    "BasicProfileIds": [
      "68357c606d966c2c14a1faff"
    ],
    "DefaultFront": 3,
    "Formation": 1
  },
  {
    "Id": "unit_1239",
    "Name": "Prince Ulther's Dragon Company",
    "Attributes": {
      "totalCost": "115",
      "height": "Standard"
    },
    "BasicProfileIds": [
      "68357c616d966c2c14a2396d"
    ],
    "DefaultFront": 5,
    "Formation": 1
  }
]