[
  {
    "Id": "profile_55b0-f49b-74d6-e55f",
    "Name": "Brother-Captain",
    "Type": "Profile",
    "Children": [
      {
        "Id": "statline_2404",
        "Info": ""
      },
      {
        "Id": "rule_3",
        "Info": ""
      },
      {
        "Id": "rule_23",
        "Info": ""
      },
      {
        "Id": "rule_4046",
        "Info": ""
      },
      {
        "Id": "rule_3590",
        "Info": "(Psychic)"
      },
      {
        "Id": "rule_3591",
        "Info": "(Psychic)"
      },
      {
        "Id": "2128-f1c4-afbc-82af",
        "Info": ""
      },
      {
        "Id": "4063-edc3-baa4-6475",
        "Info": ""
      },
      {
        "Id": "3701-b2f4-a180-cd80",
        "Info": ""
      },
      {
        "Id": "d032-863c-420d-d110",
        "Info": ""
      },
      {
        "Id": "dc6c-486b-c19-71a1",
        "Info": ""
      }
    ],
    "BaseId": "4"
  },
  {
    "Id": "profile_1072-460a-9247-6862",
    "Name": "Brotherhood Champion",
    "Type": "Profile",
    "Children": [
      {
        "Id": "statline_2405",
        "Info": ""
      },
      {
        "Id": "rule_3",
        "Info": ""
      },
      {
        "Id": "rule_23",
        "Info": ""
      },
      {
        "Id": "rule_4046",
        "Info": ""
      },
      {
        "Id": "rule_3596",
        "Info": "(Psychic)"
      },
      {
        "Id": "rule_3597",
        "Info": ""
      },
      {
        "Id": "dc6c-486b-c19-71a1",
        "Info": ""
      },
      {
        "Id": "d032-863c-420d-d110",
        "Info": ""
      }
    ],
    "BaseId": "1"
  },
  {
    "Id": "profile_1f7b-a5fe-f980-70e7",
    "Name": "Brotherhood Chaplain",
    "Type": "Profile",
    "Children": [
      {
        "Id": "statline_2406",
        "Info": ""
      },
      {
        "Id": "rule_3",
        "Info": ""
      },
      {
        "Id": "rule_23",
        "Info": ""
      },
      {
        "Id": "rule_4046",
        "Info": ""
      },
      {
        "Id": "rule_3598",
        "Info": ""
      },
      {
        "Id": "rule_3599",
        "Info": ""
      },
      {
        "Id": "rule_3600",
        "Info": ""
      },
      {
        "Id": "5fa9-c9b2-336e-6d3c",
        "Info": ""
      },
      {
        "Id": "d032-863c-420d-d110",
        "Info": ""
      }
    ],
    "BaseId": "4"
  },
  {
    "Id": "profile_f05a-b020-dc82-24e",
    "Name": "Brotherhood Librarian",
    "Type": "Profile",
    "Children": [
      {
        "Id": "statline_2407",
        "Info": ""
      },
      {
        "Id": "rule_23",
        "Info": ""
      },
      {
        "Id": "rule_4046",
        "Info": ""
      },
      {
        "Id": "rule_3988",
        "Info": "(Psychic)"
      },
      {
        "Id": "rule_3603",
        "Info": ""
      },
      {
        "Id": "8404-b7bc-4d0f-6136",
        "Info": ""
      },
      {
        "Id": "3820-e568-e53-96f2",
        "Info": ""
      },
      {
        "Id": "d032-863c-420d-d110",
        "Info": ""
      },
      {
        "Id": "d680-44f9-1df9-8e42",
        "Info": ""
      }
    ],
    "BaseId": "4"
  },
  {
    "Id": "profile_2e1f-f5d5-d4ff-f061",
    "Name": "Brotherhood Techmarine",
    "Type": "Profile",
    "Children": [
      {
        "Id": "statline_2408",
        "Info": ""
      },
      {
        "Id": "rule_3",
        "Info": ""
      },
      {
        "Id": "rule_23",
        "Info": ""
      },
      {
        "Id": "rule_4046",
        "Info": ""
      },
      {
        "Id": "rule_3605",
        "Info": ""
      },
      {
        "Id": "rule_3606",
        "Info": ""
      },
      {
        "Id": "rule_3607",
        "Info": ""
      },
      {
        "Id": "59d5-7666-1edf-125e",
        "Info": ""
      },
      {
        "Id": "8f56-9025-c58b-b16",
        "Info": ""
      },
      {
        "Id": "b291-390e-68a2-0af1",
        "Info": ""
      },
      {
        "Id": "fd2f-c151-3fed-354e",
        "Info": ""
      }
    ],
    "BaseId": "1"
  },
  {
    "Id": "profile_28af-6e37-2f1f-93d2",
    "Name": "Brotherhood Terminator Squad",
    "Type": "Profile",
    "Children": [
      {
        "Id": "statline_2409",
        "Info": ""
      },
      {
        "Id": "rule_23",
        "Info": ""
      },
      {
        "Id": "rule_4046",
        "Info": ""
      },
      {
        "Id": "rule_3608",
        "Info": "(Psychic)"
      },
      {
        "Id": "rule_2307",
        "Info": ""
      },
      {
        "Id": "rule_3989",
        "Info": ""
      },
      {
        "Id": "2128-f1c4-afbc-82af",
        "Info": ""
      },
      {
        "Id": "4063-edc3-baa4-6475",
        "Info": ""
      },
      {
        "Id": "3701-b2f4-a180-cd80",
        "Info": ""
      },
      {
        "Id": "d032-863c-420d-d110",
        "Info": ""
      },
      {
        "Id": "dc6c-486b-c19-71a1",
        "Info": ""
      }
    ],
    "BaseId": "4"
  },
  {
    "Id": "profile_7aa4-66e9-1046-f76e",
    "Name": "Castellan Crowe",
    "Type": "Profile",
    "Children": [
      {
        "Id": "statline_2410",
        "Info": ""
      },
      {
        "Id": "rule_23",
        "Info": ""
      },
      {
        "Id": "rule_3",
        "Info": ""
      },
      {
        "Id": "rule_4046",
        "Info": ""
      },
      {
        "Id": "rule_3611",
        "Info": "(Psychic)"
      },
      {
        "Id": "rule_3612",
        "Info": "(Psychic)"
      },
      {
        "Id": "73f3-22f9-3831-441a",
        "Info": ""
      },
      {
        "Id": "dae1-9183-96d9-6ccd",
        "Info": ""
      },
      {
        "Id": "d032-863c-420d-d110",
        "Info": ""
      }
    ],
    "BaseId": "4"
  },
  {
    "Id": "profile_425b-899c-7e54-95a",
    "Name": "Grand Master",
    "Type": "Profile",
    "Children": [
      {
        "Id": "statline_2411",
        "Info": ""
      },
      {
        "Id": "rule_23",
        "Info": ""
      },
      {
        "Id": "rule_4046",
        "Info": ""
      },
      {
        "Id": "rule_3615",
        "Info": ""
      },
      {
        "Id": "rule_3614",
        "Info": "(Psychic)"
      },
      {
        "Id": "rule_3616",
        "Info": ""
      },
      {
        "Id": "182b-3191-8fa-53e1",
        "Info": ""
      },
      {
        "Id": "2128-f1c4-afbc-82af",
        "Info": ""
      },
      {
        "Id": "4063-edc3-baa4-6475",
        "Info": ""
      },
      {
        "Id": "3701-b2f4-a180-cd80",
        "Info": ""
      },
      {
        "Id": "d032-863c-420d-d110",
        "Info": ""
      }
    ],
    "BaseId": "4"
  },
  {
    "Id": "profile_cb71-5829-f1d5-e7da",
    "Name": "Grand Master in Nemesis Dreadknight",
    "Type": "Profile",
    "Children": [
      {
        "Id": "statline_2412",
        "Info": ""
      },
      {
        "Id": "rule_23",
        "Info": ""
      },
      {
        "Id": "rule_24",
        "Info": ""
      },
      {
        "Id": "rule_4046",
        "Info": ""
      },
      {
        "Id": "rule_3615",
        "Info": ""
      },
      {
        "Id": "rule_3617",
        "Info": "(Psychic)"
      },
      {
        "Id": "rule_3619",
        "Info": ""
      },
      {
        "Id": "4db0-66d3-f31e-1b81",
        "Info": ""
      },
      {
        "Id": "5dd4-fb4c-f1d0-86ec",
        "Info": ""
      },
      {
        "Id": "e53e-235a-53e1-c196",
        "Info": ""
      },
      {
        "Id": "4d47-648-9923-a782",
        "Info": ""
      },
      {
        "Id": "067c-1a73-e0b0-3b80",
        "Info": ""
      },
      {
        "Id": "9291-62df-94b4-6e2c",
        "Info": ""
      },
      {
        "Id": "48db-1777-7d99-7f48",
        "Info": ""
      },
      {
        "Id": "6104-3c01-f94d-b60c",
        "Info": ""
      },
      {
        "Id": "bfc1-ea26-dbb7-6027",
        "Info": ""
      },
      {
        "Id": "28af-7d69-c39a-d65",
        "Info": ""
      },
      {
        "Id": "23f1-d294-a434-9658",
        "Info": ""
      }
    ],
    "BaseId": "18"
  },
  {
    "Id": "profile_a37-8a28-de0e-8df5",
    "Name": "Grand Master Voldus",
    "Type": "Profile",
    "Children": [
      {
        "Id": "statline_2413",
        "Info": ""
      },
      {
        "Id": "rule_23",
        "Info": ""
      },
      {
        "Id": "rule_3",
        "Info": ""
      },
      {
        "Id": "rule_4046",
        "Info": ""
      },
      {
        "Id": "rule_3620",
        "Info": "(Psychic)"
      },
      {
        "Id": "rule_3621",
        "Info": "(Psychic)"
      },
      {
        "Id": "9c20-33ed-5139-f2df",
        "Info": ""
      },
      {
        "Id": "0227-3d63-da92-f4c8",
        "Info": ""
      },
      {
        "Id": "d032-863c-420d-d110",
        "Info": ""
      }
    ],
    "BaseId": "4"
  },
  {
    "Id": "profile_5eb5-ef56-7823-faa0",
    "Name": "Land Raider",
    "Type": "Profile",
    "Children": [
      {
        "Id": "statline_2414",
        "Info": ""
      },
      {
        "Id": "rule_24",
        "Info": ""
      },
      {
        "Id": "rule_3623",
        "Info": ""
      },
      {
        "Id": "rule_3624",
        "Info": ""
      },
      {
        "Id": "da8a-8a15-3669-95d0",
        "Info": ""
      },
      {
        "Id": "4ab2-e684-f54e-151d",
        "Info": ""
      },
      {
        "Id": "543e-7730-cfbd-b972",
        "Info": ""
      },
      {
        "Id": "d032-863c-420d-d110",
        "Info": ""
      },
      {
        "Id": "ab2f-ea73-ff7f-d6f7",
        "Info": ""
      },
      {
        "Id": "506a-5ec5-393c-0b2f",
        "Info": ""
      }
    ],
    "BaseId": "3"
  },
  {
    "Id": "profile_88aa-3a4d-4ff3-1b4c",
    "Name": "Land Raider Crusader",
    "Type": "Profile",
    "Children": [
      {
        "Id": "statline_1359",
        "Info": ""
      },
      {
        "Id": "rule_24",
        "Info": ""
      },
      {
        "Id": "rule_3625",
        "Info": ""
      },
      {
        "Id": "rule_3626",
        "Info": ""
      },
      {
        "Id": "4ab2-e684-f54e-151d",
        "Info": ""
      },
      {
        "Id": "8919-feff-4724-1ddd",
        "Info": ""
      },
      {
        "Id": "543e-7730-cfbd-b972",
        "Info": ""
      },
      {
        "Id": "d032-863c-420d-d110",
        "Info": ""
      },
      {
        "Id": "ac41-4061-1972-c7d1",
        "Info": ""
      },
      {
        "Id": "506a-5ec5-393c-0b2f",
        "Info": ""
      }
    ],
    "BaseId": "3"
  },
  {
    "Id": "profile_36a8-d1b9-a5e8-b70f",
    "Name": "Land Raider Redeemer",
    "Type": "Profile",
    "Children": [
      {
        "Id": "statline_2415",
        "Info": ""
      },
      {
        "Id": "rule_24",
        "Info": ""
      },
      {
        "Id": "rule_3627",
        "Info": ""
      },
      {
        "Id": "rule_3628",
        "Info": ""
      },
      {
        "Id": "f1a0-8910-1680-5177",
        "Info": ""
      },
      {
        "Id": "4ab2-e684-f54e-151d",
        "Info": ""
      },
      {
        "Id": "543e-7730-cfbd-b972",
        "Info": ""
      },
      {
        "Id": "d032-863c-420d-d110",
        "Info": ""
      },
      {
        "Id": "ac41-4061-1972-c7d1",
        "Info": ""
      },
      {
        "Id": "506a-5ec5-393c-0b2f",
        "Info": ""
      }
    ],
    "BaseId": "3"
  },
  {
    "Id": "profile_44b5-6d17-8379-c609",
    "Name": "Razorback",
    "Type": "Profile",
    "Children": [
      {
        "Id": "statline_2416",
        "Info": ""
      },
      {
        "Id": "rule_24",
        "Info": ""
      },
      {
        "Id": "rule_3629",
        "Info": ""
      },
      {
        "Id": "4ab2-e684-f54e-151d",
        "Info": ""
      },
      {
        "Id": "d032-863c-420d-d110",
        "Info": ""
      },
      {
        "Id": "ab2f-ea73-ff7f-d6f7",
        "Info": ""
      },
      {
        "Id": "0ad2-3842-783e-ef55",
        "Info": ""
      },
      {
        "Id": "506a-5ec5-393c-0b2f",
        "Info": ""
      }
    ],
    "BaseId": "3"
  },
  {
    "Id": "profile_ceee-2a3f-1c1-3151",
    "Name": "Rhino",
    "Type": "Profile",
    "Children": [
      {
        "Id": "statline_2417",
        "Info": ""
      },
      {
        "Id": "rule_24",
        "Info": ""
      },
      {
        "Id": "rule_31",
        "Info": ""
      },
      {
        "Id": "rule_3630",
        "Info": "(Psychic)"
      },
      {
        "Id": "4ab2-e684-f54e-151d",
        "Info": ""
      },
      {
        "Id": "d032-863c-420d-d110",
        "Info": ""
      },
      {
        "Id": "506a-5ec5-393c-0b2f",
        "Info": ""
      }
    ],
    "BaseId": "3"
  },
  {
    "Id": "profile_6013-ab9b-5543-f992",
    "Name": "Stormhawk Interceptor",
    "Type": "Profile",
    "Children": [
      {
        "Id": "statline_2418",
        "Info": ""
      },
      {
        "Id": "rule_28",
        "Info": ""
      },
      {
        "Id": "rule_24",
        "Info": ""
      },
      {
        "Id": "rule_3631",
        "Info": ""
      },
      {
        "Id": "fb9-de3-ed8-a4f9",
        "Info": ""
      },
      {
        "Id": "6530-32e9-6176-f896",
        "Info": ""
      },
      {
        "Id": "e757-ca21-d20f-b58a",
        "Info": ""
      },
      {
        "Id": "ac41-4061-1972-c7d1",
        "Info": ""
      },
      {
        "Id": "ab2f-ea73-ff7f-d6f7",
        "Info": ""
      },
      {
        "Id": "c3dc-00bf-e919-5a22",
        "Info": ""
      },
      {
        "Id": "196d-145f-4eb6-1a15",
        "Info": ""
      },
      {
        "Id": "5be8-aca2-f4ed-8327",
        "Info": ""
      }
    ],
    "BaseId": "7"
  },
  {
    "Id": "profile_f8c1-1eb7-cf09-7717",
    "Name": "Stormraven Gunship",
    "Type": "Profile",
    "Children": [
      {
        "Id": "statline_2419",
        "Info": ""
      },
      {
        "Id": "rule_28",
        "Info": ""
      },
      {
        "Id": "rule_24",
        "Info": ""
      },
      {
        "Id": "rule_3632",
        "Info": ""
      },
      {
        "Id": "rule_3633",
        "Info": ""
      },
      {
        "Id": "5be8-aca2-f4ed-8327",
        "Info": ""
      },
      {
        "Id": "6340-bb29-ab5e-a0c9",
        "Info": ""
      },
      {
        "Id": "8919-feff-4724-1ddd",
        "Info": ""
      },
      {
        "Id": "ac41-4061-1972-c7d1",
        "Info": ""
      },
      {
        "Id": "ab2f-ea73-ff7f-d6f7",
        "Info": ""
      },
      {
        "Id": "c6d3-899c-3edf-dd94",
        "Info": ""
      },
      {
        "Id": "56b1-1619-dbc6-c1d",
        "Info": ""
      },
      {
        "Id": "0ad2-3842-783e-ef55",
        "Info": ""
      },
      {
        "Id": "cfbd-9a7e-949c-be07",
        "Info": ""
      },
      {
        "Id": "c3dc-00bf-e919-5a22",
        "Info": ""
      },
      {
        "Id": "196d-145f-4eb6-1a15",
        "Info": ""
      }
    ],
    "BaseId": "7"
  },
  {
    "Id": "profile_cdf0-34bc-c94b-a1cd",
    "Name": "Stormtalon Gunship",
    "Type": "Profile",
    "Children": [
      {
        "Id": "statline_2420",
        "Info": ""
      },
      {
        "Id": "rule_28",
        "Info": ""
      },
      {
        "Id": "rule_24",
        "Info": ""
      },
      {
        "Id": "rule_3634",
        "Info": ""
      },
      {
        "Id": "e757-ca21-d20f-b58a",
        "Info": ""
      },
      {
        "Id": "ac41-4061-1972-c7d1",
        "Info": ""
      },
      {
        "Id": "ab2f-ea73-ff7f-d6f7",
        "Info": ""
      },
      {
        "Id": "0ad2-3842-783e-ef55",
        "Info": ""
      },
      {
        "Id": "c3dc-00bf-e919-5a22",
        "Info": ""
      },
      {
        "Id": "196d-145f-4eb6-1a15",
        "Info": ""
      },
      {
        "Id": "454d-664a-6d82-ffaf",
        "Info": ""
      }
    ],
    "BaseId": "7"
  },
  {
    "Id": "profile_51d0-128-5b9c-c280",
    "Name": "Venerable Dreadnought",
    "Type": "Profile",
    "Children": [
      {
        "Id": "statline_2421",
        "Info": ""
      },
      {
        "Id": "rule_24",
        "Info": ""
      },
      {
        "Id": "rule_23",
        "Info": ""
      },
      {
        "Id": "rule_3635",
        "Info": "(Psychic)"
      },
      {
        "Id": "rule_4046",
        "Info": ""
      },
      {
        "Id": "efe0-8125-9e39-3187",
        "Info": ""
      },
      {
        "Id": "8b85-297f-a555-c9c1",
        "Info": ""
      },
      {
        "Id": "b5e1-2340-39f5-f072",
        "Info": ""
      },
      {
        "Id": "1871-d4ef-8c06-775a",
        "Info": ""
      },
      {
        "Id": "d032-863c-420d-d110",
        "Info": ""
      },
      {
        "Id": "0ad2-3842-783e-ef55",
        "Info": ""
      },
      {
        "Id": "57f5-eeba-73cf-e204",
        "Info": ""
      }
    ],
    "BaseId": "6"
  },
  {
    "Id": "profile_e87d-a435-e5a2-260c",
    "Name": "Interceptor Squad",
    "Type": "Profile",
    "Children": [
      {
        "Id": "statline_2422",
        "Info": ""
      },
      {
        "Id": "rule_23",
        "Info": ""
      },
      {
        "Id": "rule_4046",
        "Info": ""
      },
      {
        "Id": "rule_3636",
        "Info": ""
      },
      {
        "Id": "2128-f1c4-afbc-82af",
        "Info": ""
      },
      {
        "Id": "4063-edc3-baa4-6475",
        "Info": ""
      },
      {
        "Id": "3701-b2f4-a180-cd80",
        "Info": ""
      },
      {
        "Id": "d032-863c-420d-d110",
        "Info": ""
      },
      {
        "Id": "70d8-dc2d-387c-91ac",
        "Info": ""
      },
      {
        "Id": "dc6c-486b-c19-71a1",
        "Info": ""
      }
    ],
    "BaseId": "1"
  },
  {
    "Id": "profile_a1ef-3a29-210b-de07",
    "Name": "Nemesis Dreadknight",
    "Type": "Profile",
    "Children": [
      {
        "Id": "statline_2423",
        "Info": ""
      },
      {
        "Id": "rule_23",
        "Info": ""
      },
      {
        "Id": "rule_24",
        "Info": ""
      },
      {
        "Id": "rule_4046",
        "Info": ""
      },
      {
        "Id": "rule_3641",
        "Info": "(Psychic)"
      },
      {
        "Id": "rule_3642",
        "Info": ""
      },
      {
        "Id": "5dd4-fb4c-f1d0-86ec",
        "Info": ""
      },
      {
        "Id": "e53e-235a-53e1-c196",
        "Info": ""
      },
      {
        "Id": "4d47-648-9923-a782",
        "Info": ""
      },
      {
        "Id": "9291-62df-94b4-6e2c",
        "Info": ""
      },
      {
        "Id": "48db-1777-7d99-7f48",
        "Info": ""
      },
      {
        "Id": "bfc1-ea26-dbb7-6027",
        "Info": ""
      },
      {
        "Id": "28af-7d69-c39a-d65",
        "Info": ""
      }
    ],
    "BaseId": "18"
  },
  {
    "Id": "profile_ca57-5b17-a4ed-f420",
    "Name": "Paladin Squad",
    "Type": "Profile",
    "Children": [
      {
        "Id": "statline_2424",
        "Info": ""
      },
      {
        "Id": "rule_23",
        "Info": ""
      },
      {
        "Id": "rule_4046",
        "Info": ""
      },
      {
        "Id": "rule_3643",
        "Info": "(Psychic)"
      },
      {
        "Id": "2128-f1c4-afbc-82af",
        "Info": ""
      },
      {
        "Id": "4063-edc3-baa4-6475",
        "Info": ""
      },
      {
        "Id": "3701-b2f4-a180-cd80",
        "Info": ""
      },
      {
        "Id": "d032-863c-420d-d110",
        "Info": ""
      },
      {
        "Id": "dc6c-486b-c19-71a1",
        "Info": ""
      }
    ],
    "BaseId": "4"
  },
  {
    "Id": "profile_e6e3-290b-6bef-ddd7",
    "Name": "Purgation Squad",
    "Type": "Profile",
    "Children": [
      {
        "Id": "statline_2425",
        "Info": ""
      },
      {
        "Id": "rule_23",
        "Info": ""
      },
      {
        "Id": "rule_4046",
        "Info": ""
      },
      {
        "Id": "rule_3645",
        "Info": ""
      },
      {
        "Id": "2128-f1c4-afbc-82af",
        "Info": ""
      },
      {
        "Id": "4063-edc3-baa4-6475",
        "Info": ""
      },
      {
        "Id": "3701-b2f4-a180-cd80",
        "Info": ""
      },
      {
        "Id": "d032-863c-420d-d110",
        "Info": ""
      },
      {
        "Id": "70d8-dc2d-387c-91ac",
        "Info": ""
      },
      {
        "Id": "dc6c-486b-c19-71a1",
        "Info": ""
      }
    ],
    "BaseId": "1"
  },
  {
    "Id": "profile_1ca-2f4a-980e-a0ad",
    "Name": "Purifier Squad",
    "Type": "Profile",
    "Children": [
      {
        "Id": "statline_2426",
        "Info": ""
      },
      {
        "Id": "rule_23",
        "Info": ""
      },
      {
        "Id": "rule_4046",
        "Info": ""
      },
      {
        "Id": "rule_3646",
        "Info": ""
      },
      {
        "Id": "2128-f1c4-afbc-82af",
        "Info": ""
      },
      {
        "Id": "4063-edc3-baa4-6475",
        "Info": ""
      },
      {
        "Id": "3701-b2f4-a180-cd80",
        "Info": ""
      },
      {
        "Id": "73f3-22f9-3831-441a",
        "Info": ""
      },
      {
        "Id": "d032-863c-420d-d110",
        "Info": ""
      },
      {
        "Id": "70d8-dc2d-387c-91ac",
        "Info": ""
      },
      {
        "Id": "dc6c-486b-c19-71a1",
        "Info": ""
      }
    ],
    "BaseId": "1"
  },
  {
    "Id": "profile_3d57-16ca-bf72-e43a",
    "Name": "Strike Squad",
    "Type": "Profile",
    "Children": [
      {
        "Id": "statline_2427",
        "Info": ""
      },
      {
        "Id": "rule_23",
        "Info": ""
      },
      {
        "Id": "rule_21",
        "Info": ""
      },
      {
        "Id": "rule_4046",
        "Info": ""
      },
      {
        "Id": "rule_3651",
        "Info": "(Psychic)"
      },
      {
        "Id": "70d8-dc2d-387c-91ac",
        "Info": ""
      },
      {
        "Id": "dc6c-486b-c19-71a1",
        "Info": ""
      },
      {
        "Id": "2128-f1c4-afbc-82af",
        "Info": ""
      },
      {
        "Id": "4063-edc3-baa4-6475",
        "Info": ""
      },
      {
        "Id": "3701-b2f4-a180-cd80",
        "Info": ""
      },
      {
        "Id": "d032-863c-420d-d110",
        "Info": ""
      }
    ],
    "BaseId": "1"
  },
  {
    "Id": "profile_357b-e9fc-505d-c82d",
    "Name": "Grey Knights Thunderhawk Gunship",
    "Type": "Profile",
    "Children": [
      {
        "Id": "statline_2428",
        "Info": ""
      },
      {
        "Id": "rule_28",
        "Info": ""
      },
      {
        "Id": "rule_24",
        "Info": ""
      },
      {
        "Id": "rule_3652",
        "Info": ""
      },
      {
        "Id": "rule_3653",
        "Info": ""
      },
      {
        "Id": "rule_2258",
        "Info": ""
      },
      {
        "Id": "fdc6-4762-3739-adb6",
        "Info": ""
      },
      {
        "Id": "e9be-6b58-f0bd-9a1f",
        "Info": ""
      },
      {
        "Id": "93c3-67b4-925f-c9f2",
        "Info": ""
      },
      {
        "Id": "27fe-af10-946e-78ed",
        "Info": ""
      },
      {
        "Id": "2ac2-e8ff-d331-eb78",
        "Info": ""
      },
      {
        "Id": "ab2f-ea73-ff7f-d6f7",
        "Info": ""
      }
    ],
    "BaseId": "3"
  }
]